winspeech.py
winspeech-1.0.1.dist-info/DESCRIPTION.rst
winspeech-1.0.1.dist-info/METADATA
winspeech-1.0.1.dist-info/RECORD
winspeech-1.0.1.dist-info/WHEEL
winspeech-1.0.1.dist-info/metadata.json
winspeech-1.0.1.dist-info/top_level.txt
