Metadata-Version: 1.1
Name: winspeech
Version: 1.0.1
Summary: Speech recognition and synthesis module for Windows - Python 2 and 3.
Home-page: https://github.com/areebbeigh/winspeech
Author: Areeb Beigh
Author-email: areebbeigh@gmail.com
License: Apache License 2.0
Keywords: speech recognition synthesis tts text-to-speech windows SAPI
Platform: UNKNOWN
Classifier: Development Status :: 4 - Beta
Classifier: Intended Audience :: Developers
Classifier: Operating System :: Microsoft :: Windows
Classifier: Topic :: Text Processing :: Linguistic
Classifier: Topic :: Software Development :: Libraries :: Python Modules
Classifier: Topic :: Home Automation
Classifier: Topic :: Scientific/Engineering :: Human Machine Interfaces
Classifier: Topic :: Multimedia :: Sound/Audio :: Speech
Classifier: License :: OSI Approved :: Apache Software License
Classifier: Programming Language :: Python :: 2
Classifier: Programming Language :: Python :: 2.6
Classifier: Programming Language :: Python :: 2.7
Classifier: Programming Language :: Python :: 3
Classifier: Programming Language :: Python :: 3.3
Classifier: Programming Language :: Python :: 3.4
Classifier: Programming Language :: Python :: 3.5
